skcom/__init__.py
skcom/asyncrecv.py
skcom/crypto.py
skcom/exception.py
skcom/helper.py
skcom/oldrecv.py
skcom/receiver.py
skcom/conf/cmdlets.txt
skcom/conf/logging.yaml
skcom/conf/skcom.yaml
skcom/samples/bot.py
skcom/samples/kline.py
skcom/samples/ticks.py
skcom/tests/__init__.py
skcom/tests/test_helper.py
skcom/tools/cfdec.py
skcom/tools/cfenc.py
skcom/tools/clean.py
skcom/tools/setup.py
skcom-0.9.9.dist-info/LICENSE
skcom-0.9.9.dist-info/METADATA
skcom-0.9.9.dist-info/WHEEL
skcom-0.9.9.dist-info/top_level.txt
skcom-0.9.9.dist-info/RECORD
