Metadata-Version: 2.1
Name: skcom
Version: 0.9.9
Summary: Get stock informations by Capital API.
Home-page: https://github.com/tacosync/skcom
Author: Raymond Wu
License: MIT
Platform: UNKNOWN
Requires-Python: >=3.7
Requires-Dist: packaging
Requires-Dist: requests
Requires-Dist: busm (>=0.9.5)
Requires-Dist: PyYAML (>=5.1)
Requires-Dist: cryptography (>=2.9.0)
Requires-Dist: comtypes (>=1.1.7) ; platform_system == "Windows"
Requires-Dist: pywin32 (>=1.0) ; platform_system == "Windows"
